scdl/__init__.py
scdl/scdl.cfg
scdl/scdl.py
scdl/utils.py
scdl/patches/__init__.py
scdl/patches/mutagen_postprocessor.py
scdl/patches/old_archive_ids.py
scdl/patches/original_filename_preprocessor.py
scdl/patches/switch_outtmpl_preprocessor.py
scdl/patches/sync_download_archive.py
scdl/patches/thumbnail_selection.py
scdl/patches/trim_filenames.py
scdl-3.0.3.dist-info/licenses/AUTHORS
scdl-3.0.3.dist-info/licenses/LICENSE
scdl-3.0.3.dist-info/METADATA
scdl-3.0.3.dist-info/WHEEL
scdl-3.0.3.dist-info/entry_points.txt
scdl-3.0.3.dist-info/top_level.txt
scdl-3.0.3.dist-info/RECORD
