Metadata-Version: 2.4
Name: scdl
Version: 3.0.3
Summary: Download Music from Souncloud
Author: 7x11x13, FlyinGrub
Project-URL: Issues, https://github.com/scdl-org/scdl/issues
Project-URL: Repository, https://github.com/scdl-org/scdl
Project-URL: Changelog, https://github.com/scdl-org/scdl/blob/master/CHANGELOG.md
Classifier: Programming Language :: Python
Classifier: Development Status :: 5 - Production/Stable
Classifier: License :: OSI Approved :: GNU General Public License v2 (GPLv2)
Classifier: Operating System :: OS Independent
Classifier: Programming Language :: Python :: 3.9
Classifier: Programming Language :: Python :: 3.10
Classifier: Programming Language :: Python :: 3.11
Classifier: Programming Language :: Python :: 3.12
Classifier: Topic :: Internet
Classifier: Topic :: Multimedia :: Sound/Audio
Requires-Python: >=3.9.0
License-File: LICENSE
License-File: AUTHORS
Requires-Dist: docopt-ng>=0.9.0
Requires-Dist: mutagen>=1.47.0
Requires-Dist: soundcloud-v2>=1.6.1
Requires-Dist: yt-dlp>=2025.2.19
Dynamic: license-file
